kademlia/__init__.py
kademlia/crawling.py
kademlia/network.py
kademlia/node.py
kademlia/protocol.py
kademlia/routing.py
kademlia/storage.py
kademlia/utils.py
kademlia/tests/__init__.py
kademlia/tests/conftest.py
kademlia/tests/test_node.py
kademlia/tests/test_routing.py
kademlia/tests/test_server.py
kademlia/tests/test_storage.py
kademlia/tests/test_utils.py
secure_kademlia-0.0.0.dist-info/LICENSE
secure_kademlia-0.0.0.dist-info/METADATA
secure_kademlia-0.0.0.dist-info/WHEEL
secure_kademlia-0.0.0.dist-info/top_level.txt
secure_kademlia-0.0.0.dist-info/RECORD
