Metadata-Version: 2.1
Name: secure-kademlia
Version: 0.0.0
Summary: Kademlia is a distributed hash table for decentralized peer-to-peer computer networks.
Home-page: https://github.com/beardog108/kademlia
Author: Brian Muller
Author-email: bamuller@gmail.com
License: MIT
Platform: UNKNOWN
Classifier: Development Status :: 5 - Production/Stable
Classifier: Intended Audience :: Developers
Classifier: License :: OSI Approved :: MIT License
Classifier: Operating System :: OS Independent
Classifier: Programming Language :: Python
Classifier: Programming Language :: Python :: 3
Classifier: Programming Language :: Python :: 3.6
Classifier: Programming Language :: Python :: 3.7
Classifier: Topic :: Software Development :: Libraries :: Python Modules
Requires-Python: ~=3.6
Requires-Dist: rpcudp (>=4.0.1)
Requires-Dist: umsgpack
